phageai/__init__.py
phageai/phageai_auth.py
phageai/platform/__init__.py
phageai/platform/phageai_api.py
phageai-1.0.0.dist-info/LICENSE
phageai-1.0.0.dist-info/METADATA
phageai-1.0.0.dist-info/WHEEL
phageai-1.0.0.dist-info/top_level.txt
phageai-1.0.0.dist-info/RECORD
