Metadata-Version: 2.1
Name: phageai
Version: 1.0.0
Summary: PhageAI is an AI-driven software platform using advanced Machine Learning and Natural Language Processing techniques for deeper understanding of the bacteriophages genomics.
Home-page: https://github.com/phageaisa/phageai
Download-URL: https://github.com/phageaisa/phageai/archive/v1.0.0.tar.gz
Author: PhageAI S.A.
Author-email: contact@phage.ai
License: MIT
Keywords: bacteriophages,phages,phage therapy,phage research,phage lifecycle,phage taxonomy,phage similarity,phage characteristics,virulent phage,temperate phage,chronic phage
Classifier: Development Status :: 3 - Alpha
Classifier: License :: OSI Approved :: MIT License
Classifier: Programming Language :: Python :: 3.8
Requires-Python: >=3.8
License-File: LICENSE
Requires-Dist: requests >=2.26.0
Requires-Dist: pytest >=6.2.5
Requires-Dist: black >=20.8b1
